functioncalming/__init__.py
functioncalming/client.py
functioncalming/context.py
functioncalming/models.py
functioncalming/types.py
functioncalming/utils.py
functioncalming-0.0.24.dist-info/METADATA
functioncalming-0.0.24.dist-info/WHEEL
functioncalming-0.0.24.dist-info/licenses/LICENSE
functioncalming-0.0.24.dist-info/RECORD
