Metadata-Version: 2.4
Name: functioncalming
Version: 0.0.24
Summary: Robust and reliable OpenAI tool calling
License: MIT
License-File: LICENSE
Keywords: openai,function-calling,pydantic,validation,llm,tool-calling,retry,structured-ouputs
Author: Philipp Dowling
Author-email: phdowling@users.noreply.github.com
Requires-Python: >=3.12,<4.0
Classifier: License :: OSI Approved :: MIT License
Classifier: Programming Language :: Python :: 3
Classifier: Programming Language :: Python :: 3.12
Classifier: Programming Language :: Python :: 3.13
Classifier: Programming Language :: Python :: 3.14
Requires-Dist: docstring-parser (>=0.17,<0.18)
Requires-Dist: openai (>=2.7.1)
Requires-Dist: pydantic (>=2.12.4)
Requires-Dist: pytest-httpx (>=0.35.0,<0.36.0)
Project-URL: Homepage, https://github.com/phdowling/functioncalming
Project-URL: Repository, https://github.com/phdowling/functioncalming
